delegatum/__init__.py
delegatum/delegatum.py
delegatum-1.0.0.dist-info/LICENSE
delegatum-1.0.0.dist-info/WHEEL
delegatum-1.0.0.dist-info/METADATA
delegatum-1.0.0.dist-info/RECORD
