Metadata-Version: 2.1
Name: delegatum
Version: 1.0.0
Summary: Simple cascading/nested scope/namespace manager
Home-page: https://github.com/datagazing/delegatum
Author: Brendan Strejcek
Author-email: brendan@datagazing.com
Requires-Python: >=3.7
Classifier: License :: OSI Approved :: MIT License
